epdfpy/__init__.py
epdfpy/definitions.py
epdfpy/run_ui.py
epdfpy/util.py
epdfpy/assets/Thumbs.db
epdfpy/assets/colorcube256.csv
epdfpy/assets/colorcube512.csv
epdfpy/assets/example.gif
epdfpy/assets/mask_data.json
epdfpy/assets/mask_data.txt
epdfpy/assets/mask_data2.txt
epdfpy/assets/sample_azavg.csv
epdfpy/assets/Parameter_files/Amorphous_SiO2_azav_0.00167.txt
epdfpy/assets/Parameter_files/Kirkland_2010.txt
epdfpy/assets/Parameter_files/Lobato_2014.txt
epdfpy/assets/Parameter_files/Periodic Table of Elements.csv
epdfpy/assets/Parameter_files/atomicNumber-symbol.csv
epdfpy/assets/css/Combinear.qss
epdfpy/assets/css/STYLE.qss
epdfpy/assets/mask/berkeley_full.csv
epdfpy/assets/mask/mask_data.csv
epdfpy/assets/mask/mask_data2.csv
epdfpy/calculate/__init__.py
epdfpy/calculate/autofit.py
epdfpy/calculate/beam_stopper.py
epdfpy/calculate/elliptical_correction.py
epdfpy/calculate/image_process.py
epdfpy/calculate/pdf_calculator.py
epdfpy/calculate/polar_transform.py
epdfpy/calculate/q_range_selector.py
epdfpy/datacube/__init__.py
epdfpy/datacube/cube.py
epdfpy/datacube/datacube.py
epdfpy/file/__init__.py
epdfpy/file/file.py
epdfpy/file/load.py
epdfpy/settings/data_quality.csv
epdfpy/settings/default.json
epdfpy/settings/element_presets.json
epdfpy/ui/__init__.py
epdfpy/ui/advanced_fit.py
epdfpy/ui/main.py
epdfpy/ui/pdfanalysis.py
epdfpy/ui/profile_extraction.py
epdfpy/ui/ui_util.py
epdfpy/ui/roi_selector/__init__.py
epdfpy/ui/roi_selector/mask_module.py
epdfpy/ui/roi_selector/roi_selector.py
epdfpy/ui/selection_analysis/__init__.py
epdfpy/ui/selection_analysis/averaging_multiple_gr.py
epdfpy/ui/selection_analysis/column_selector.py
epdfpy-0.0.1.dist-info/LICENSE
epdfpy-0.0.1.dist-info/METADATA
epdfpy-0.0.1.dist-info/WHEEL
epdfpy-0.0.1.dist-info/entry_points.txt
epdfpy-0.0.1.dist-info/top_level.txt
epdfpy-0.0.1.dist-info/RECORD
