Metadata-Version: 2.1
Name: epdfpy
Version: 0.0.1
Summary: Python GUI module for pair distribution analysis on amorphous material
Home-page: https://github.com/GWlab-SKKU/ePDFpy
Author: M.H.Kim, P.S.Kim and K-.Lee
Author-email: vader0210@skku.edu
Classifier: Programming Language :: Python :: 3
Classifier: License :: OSI Approved :: GNU General Public License v3 (GPLv3)
Classifier: Operating System :: OS Independent
Requires-Python: >=3.8
License-File: LICENSE
